{
  "digestPath": ".codectx/verify/faults/fault-fc0c8590.digest.json",
  "fault": {
    "artifactPath": ".codectx/verify/faults/fault-fc0c8590.json",
    "faultId": "fault-fc0c8590",
    "importedAt": "2026-07-01T16:57:25.982901900+00:00",
    "kind": "runtime_digest",
    "schema": "obscur.m0.capture.v1",
    "symptomIds": [],
    "title": "Imported runtime capture digest"
  },
  "schema": "verify.fault.import@0.1.0",
  "sourcePath": ".codectx/verify/client-sessions/csess-631c3bba5207/captures/cap-334c7c538445/digest.json"
}
